{
    "CO": {
        "baseline": "CO",
        "classifier": "Gases",
        "subscript": null,
        "aqs_unit_code": 8,
        "averaging": null,
        "usepa_targets": false,
        "criteria": true,
        "aqs_param_code": 42101,
        "custom": false,
        "unit_info": {
            "Unit Code": 8,
            "Description": "Parts per Billion",
            "Label": "ppbv",
            "Conditions": null,
            "Context": "by volume",
            "SDFS": "CO, NO, NO2, NOx, O3, SOx, SO2",
            "Classification": "Gases"
        }
    },
    "DP": {
        "baseline": "Dew point",
        "classifier": "Met",
        "subscript": null,
        "aqs_unit_code": 17,
        "averaging": null,
        "usepa_targets": false,
        "criteria": false,
        "aqs_param_code": 62103,
        "custom": false,
        "unit_info": {
            "Unit Code": 17,
            "Description": "Degrees",
            "Label": "\u00b0C",
            "Conditions": null,
            "Context": "Centigrade",
            "SDFS": "Temp, DP",
            "Classification": "Met"
        }
    },
    "NO": {
        "baseline": "NO",
        "classifier": "Gases",
        "subscript": null,
        "aqs_unit_code": 8,
        "averaging": null,
        "usepa_targets": false,
        "criteria": false,
        "aqs_param_code": 42601,
        "custom": false,
        "unit_info": {
            "Unit Code": 8,
            "Description": "Parts per Billion",
            "Label": "ppbv",
            "Conditions": null,
            "Context": "by volume",
            "SDFS": "CO, NO, NO2, NOx, O3, SOx, SO2",
            "Classification": "Gases"
        }
    },
    "NO2": {
        "baseline": "NO",
        "classifier": "Gases",
        "subscript": "2",
        "aqs_unit_code": 8,
        "averaging": null,
        "usepa_targets": false,
        "criteria": true,
        "aqs_param_code": 42602,
        "custom": false,
        "unit_info": {
            "Unit Code": 8,
            "Description": "Parts per Billion",
            "Label": "ppbv",
            "Conditions": null,
            "Context": "by volume",
            "SDFS": "CO, NO, NO2, NOx, O3, SOx, SO2",
            "Classification": "Gases"
        }
    },
    "NOx": {
        "baseline": "NO",
        "classifier": "Gases",
        "subscript": "x",
        "aqs_unit_code": 8,
        "averaging": null,
        "usepa_targets": false,
        "criteria": false,
        "aqs_param_code": 42603,
        "custom": false,
        "unit_info": {
            "Unit Code": 8,
            "Description": "Parts per Billion",
            "Label": "ppbv",
            "Conditions": null,
            "Context": "by volume",
            "SDFS": "CO, NO, NO2, NOx, O3, SOx, SO2",
            "Classification": "Gases"
        }
    },
    "O3": {
        "baseline": "O",
        "classifier": "Gases",
        "subscript": "3",
        "aqs_unit_code": 8,
        "averaging": [
            "1-hour"
        ],
        "usepa_targets": true,
        "criteria": true,
        "aqs_param_code": 44201,
        "custom": false,
        "unit_info": {
            "Unit Code": 8,
            "Description": "Parts per Billion",
            "Label": "ppbv",
            "Conditions": null,
            "Context": "by volume",
            "SDFS": "CO, NO, NO2, NOx, O3, SOx, SO2",
            "Classification": "Gases"
        }
    },
    "PM1": {
        "baseline": "PM",
        "classifier": "PM",
        "subscript": "1",
        "aqs_unit_code": 105,
        "averaging": null,
        "usepa_targets": false,
        "criteria": false,
        "aqs_param_code": "",
        "custom": false,
        "unit_info": {
            "Unit Code": 105,
            "Description": "Micrograms per Cubic Meter",
            "Label": "\u00b5g/m\u00b3",
            "Conditions": "Local Conditions",
            "Context": null,
            "SDFS": "PM1, PM25, PM10",
            "Classification": "PM"
        }
    },
    "PM10": {
        "baseline": "PM",
        "classifier": "PM",
        "subscript": "10",
        "aqs_unit_code": 105,
        "averaging": null,
        "usepa_targets": false,
        "criteria": true,
        "aqs_param_code": 81102,
        "custom": false,
        "unit_info": {
            "Unit Code": 105,
            "Description": "Micrograms per Cubic Meter",
            "Label": "\u00b5g/m\u00b3",
            "Conditions": "Local Conditions",
            "Context": null,
            "SDFS": "PM1, PM25, PM10",
            "Classification": "PM"
        }
    },
    "PM25": {
        "baseline": "PM",
        "classifier": "PM",
        "subscript": "2.5",
        "aqs_unit_code": 105,
        "averaging": [
            "1-hour",
            "24-hour"
        ],
        "usepa_targets": true,
        "criteria": true,
        "aqs_param_code": 88101,
        "custom": false,
        "unit_info": {
            "Unit Code": 105,
            "Description": "Micrograms per Cubic Meter",
            "Label": "\u00b5g/m\u00b3",
            "Conditions": "Local Conditions",
            "Context": null,
            "SDFS": "PM1, PM25, PM10",
            "Classification": "PM"
        }
    },
    "SO2": {
        "baseline": "SO",
        "classifier": "Gases",
        "subscript": "2",
        "aqs_unit_code": 8,
        "averaging": null,
        "usepa_targets": false,
        "criteria": true,
        "aqs_param_code": 42401,
        "custom": false,
        "unit_info": {
            "Unit Code": 8,
            "Description": "Parts per Billion",
            "Label": "ppbv",
            "Conditions": null,
            "Context": "by volume",
            "SDFS": "CO, NO, NO2, NOx, O3, SOx, SO2",
            "Classification": "Gases"
        }
    },
    "SOx": {
        "baseline": "SO",
        "classifier": "Gases",
        "subscript": "x",
        "aqs_unit_code": 8,
        "averaging": null,
        "usepa_targets": false,
        "criteria": false,
        "aqs_param_code": "",
        "custom": false,
        "unit_info": {
            "Unit Code": 8,
            "Description": "Parts per Billion",
            "Label": "ppbv",
            "Conditions": null,
            "Context": "by volume",
            "SDFS": "CO, NO, NO2, NOx, O3, SOx, SO2",
            "Classification": "Gases"
        }
    },
    "Temp": {
        "baseline": "Temperature",
        "classifier": "Met",
        "subscript": null,
        "aqs_unit_code": 17,
        "averaging": null,
        "usepa_targets": false,
        "criteria": false,
        "aqs_param_code": 62101,
        "custom": false,
        "unit_info": {
            "Unit Code": 17,
            "Description": "Degrees",
            "Label": "\u00b0C",
            "Conditions": null,
            "Context": "Centigrade",
            "SDFS": "Temp, DP",
            "Classification": "Met"
        }
    },
    "RH": {
        "baseline": "Relative Humidity",
        "classifier": "Met",
        "subscript": null,
        "aqs_unit_code": 19,
        "averaging": null,
        "usepa_targets": false,
        "criteria": false,
        "aqs_param_code": 62201,
        "custom": false,
        "unit_info": {
            "Unit Code": 19,
            "Description": "Percent",
            "Label": "%",
            "Conditions": null,
            "Context": "Relative Humidity",
            "SDFS": "RH",
            "Classification": "Met"
        }
    },
    "Press": {
        "baseline": "Pressure",
        "classifier": "Met",
        "subscript": null,
        "aqs_unit_code": 129,
        "averaging": null,
        "usepa_targets": false,
        "criteria": false,
        "aqs_param_code": 68108,
        "custom": false,
        "unit_info": {
            "Unit Code": 129,
            "Description": "Kilopascal",
            "Label": "kPa",
            "Conditions": null,
            "Context": null,
            "SDFS": "Press",
            "Classification": "Met"
        }
    },
    "WD": {
        "baseline": "Wind Direction",
        "classifier": "Met",
        "subscript": null,
        "aqs_unit_code": 14,
        "averaging": null,
        "usepa_targets": false,
        "criteria": false,
        "aqs_param_code": 61102,
        "custom": false,
        "unit_info": {
            "Unit Code": 14,
            "Description": "Degrees",
            "Label": "\u00b0 (compass)",
            "Conditions": null,
            "Context": "Compass",
            "SDFS": "WD",
            "Classification": "Met"
        }
    },
    "WS": {
        "baseline": "Wind Speed",
        "classifier": "Met",
        "subscript": null,
        "aqs_unit_code": 11,
        "averaging": null,
        "usepa_targets": false,
        "criteria": false,
        "aqs_param_code": 61101,
        "custom": false,
        "unit_info": {
            "Unit Code": 11,
            "Description": "Meters per Second",
            "Label": "m/s",
            "Conditions": null,
            "Context": null,
            "SDFS": "WS",
            "Classification": "Met"
        }
    }
}
